{"skeleton":{"hash":"gZQjxtdsgSu6x0Fklf5OGn2owbk","spine":"3.3.07","width":0,"height":0},"bones":[{"name":"root"},{"name":"bone","parent":"root"}],"slots":[{"name":"dds","bone":"bone","blend":"additive"}],"skins":{"default":{"dds":{"00000":{"width":640,"height":60},"00001":{"width":640,"height":60},"00002":{"width":640,"height":60},"00003":{"width":640,"height":60},"00004":{"width":640,"height":60},"00005":{"width":640,"height":60},"00006":{"width":640,"height":60},"00007":{"width":640,"height":60},"00008":{"width":640,"height":60},"00009":{"width":640,"height":60},"00010":{"width":640,"height":60}}}},"animations":{"animation":{"slots":{"dds":{"color":[{"time":0,"color":"ffffff00"},{"time":0.0333,"color":"ffffffff","curve":"stepped"},{"time":0.7,"color":"ffffffff"},{"time":0.7666,"color":"ffffff00"}],"attachment":[{"time":0,"name":null},{"time":0.0333,"name":"00000"},{"time":0.1,"name":"00001"},{"time":0.1666,"name":"00002"},{"time":0.2333,"name":"00003"},{"time":0.3,"name":"00004"},{"time":0.3666,"name":"00005"},{"time":0.4333,"name":"00006"},{"time":0.5,"name":"00007"},{"time":0.5666,"name":"00008"},{"time":0.6333,"name":"00009"},{"time":0.7,"name":"00010"},{"time":0.7666,"name":null}]}},"bones":{"root":{"rotate":[{"time":0,"angle":0,"curve":"stepped"},{"time":0.7666,"angle":0}],"translate":[{"time":0,"x":0,"y":0,"curve":"stepped"},{"time":0.7666,"x":0,"y":0}],"scale":[{"time":0,"x":1,"y":1,"curve":"stepped"},{"time":0.7666,"x":1,"y":1}],"shear":[{"time":0,"x":0,"y":0,"curve":"stepped"},{"time":0.7666,"x":0,"y":0}]},"bone":{"rotate":[{"time":0,"angle":0,"curve":"stepped"},{"time":0.7666,"angle":0}],"translate":[{"time":0,"x":0,"y":0,"curve":"stepped"},{"time":0.7666,"x":0,"y":0}],"scale":[{"time":0,"x":1,"y":1,"curve":"stepped"},{"time":0.7666,"x":1,"y":1}],"shear":[{"time":0,"x":0,"y":0,"curve":"stepped"},{"time":0.7666,"x":0,"y":0}]}}}}}